cicotunnel/__init__.py
cicotunnel/main.py
cico_tunnel-1.1.5.dist-info/METADATA
cico_tunnel-1.1.5.dist-info/WHEEL
cico_tunnel-1.1.5.dist-info/entry_points.txt
cico_tunnel-1.1.5.dist-info/top_level.txt
cico_tunnel-1.1.5.dist-info/RECORD
