Metadata-Version: 2.1
Name: cico-tunnel
Version: 1.1.5
Summary: Expose your localhost to the web. Like a Ngrok
Home-page: https://github.com/hugosantoslisboa/cico-tunnel
Author: Hugo Santos Lisboa
Author-email: hugosantoslisboa@gmail.com
Classifier: Programming Language :: Python :: 3
Classifier: License :: OSI Approved :: MIT License
Classifier: Operating System :: OS Independent
Requires-Python: >=3.6
Requires-Dist: colorama
